[{"AdminLevel_Child":"8","AdminLevel_Parent":"4","Children":"","ChildrenIndexes":"","CountryCode_Child":"FM","CountryCode_Parent":"FM","Id":3819412,"Id_Child":"relation/3819412","Id_Parent":"relation/3819422","Index":0,"Name_Child":"Dalipeebinaew","Name_Parent":"Yap"},{"AdminLevel_Child":"8","AdminLevel_Parent":"4","Children":"","ChildrenIndexes":"","CountryCode_Child":"FM","CountryCode_Parent":"FM","Id":3819413,"Id_Child":"relation/3819413","Id_Parent":"relation/3819422","Index":1,"Name_Child":"Fanif","Name_Parent":"Yap"},{"AdminLevel_Child":"8","AdminLevel_Parent":"4","Children":"","ChildrenIndexes":"","CountryCode_Child":"FM","CountryCode_Parent":"FM","Id":3819414,"Id_Child":"relation/3819414","Id_Parent":"relation/3819422","Index":2,"Name_Child":"Gagil","Name_Parent":"Yap"},{"AdminLevel_Child":"8","AdminLevel_Parent":"4","Children":"","ChildrenIndexes":"","CountryCode_Child":"FM","CountryCode_Parent":"FM","Id":3819415,"Id_Child":"relation/3819415","Id_Parent":"relation/3819422","Index":3,"Name_Child":"Gilmaan","Name_Parent":"Yap"},{"AdminLevel_Child":"8","AdminLevel_Parent":"4","Children":"","ChildrenIndexes":"","CountryCode_Child":"FM","CountryCode_Parent":"FM","Id":3819416,"Id_Child":"relation/3819416","Id_Parent":"relation/3819422","Index":4,"Name_Child":"Kanifaay","Name_Parent":"Yap"},{"AdminLevel_Child":"8","AdminLevel_Parent":"4","Children":"","ChildrenIndexes":"","CountryCode_Child":"FM","CountryCode_Parent":"FM","Id":3819417,"Id_Child":"relation/3819417","Id_Parent":"relation/3819422","Index":5,"Name_Child":"Maap′","Name_Parent":"Yap"},{"AdminLevel_Child":"8","AdminLevel_Parent":"4","Children":"","ChildrenIndexes":"","CountryCode_Child":"FM","CountryCode_Parent":"FM","Id":3819418,"Id_Child":"relation/3819418","Id_Parent":"relation/3819422","Index":6,"Name_Child":"Rumung","Name_Parent":"Yap"},{"AdminLevel_Child":"8","AdminLevel_Parent":"4","Children":"","ChildrenIndexes":"","CountryCode_Child":"FM","CountryCode_Parent":"FM","Id":3819419,"Id_Child":"relation/3819419","Id_Parent":"relation/3819422","Index":7,"Name_Child":"Ruul","Name_Parent":"Yap"},{"AdminLevel_Child":"8","AdminLevel_Parent":"4","Children":"","ChildrenIndexes":"","CountryCode_Child":"FM","CountryCode_Parent":"FM","Id":3819420,"Id_Child":"relation/3819420","Id_Parent":"relation/3819422","Index":8,"Name_Child":"Tomil","Name_Parent":"Yap"},{"AdminLevel_Child":"8","AdminLevel_Parent":"4","Children":"","ChildrenIndexes":"","CountryCode_Child":"FM","CountryCode_Parent":"FM","Id":3819421,"Id_Child":"relation/3819421","Id_Parent":"relation/3819422","Index":9,"Name_Child":"Weeloey","Name_Parent":"Yap"},{"AdminLevel_Child":"4","AdminLevel_Parent":"2","Children":"relation/3819412, relation/3819413, relation/3819414, relation/3819415, relation/3819416, relation/3819417, relation/3819418, relation/3819419, relation/3819420, relation/3819421, relation/3819437, relation/3819441","ChildrenIndexes":"0, 1, 2, 3, 4, 5, 6, 7, 8, 9, 11, 12","CountryCode_Child":"FM","CountryCode_Parent":"FM","Id":3819422,"Id_Child":"relation/3819422","Id_Parent":"relation/571802","Index":10,"Name_Child":"Yap","Name_Parent":"Micronesia / Federated States of Micronesia"},{"AdminLevel_Child":"8","AdminLevel_Parent":"4","Children":"","ChildrenIndexes":"","CountryCode_Child":"FM","CountryCode_Parent":"FM","Id":3819437,"Id_Child":"relation/3819437","Id_Parent":"relation/3819422","Index":11,"Name_Child":"Elato","Name_Parent":"Yap"},{"AdminLevel_Child":"8","AdminLevel_Parent":"4","Children":"","ChildrenIndexes":"","CountryCode_Child":"FM","CountryCode_Parent":"FM","Id":3819441,"Id_Child":"relation/3819441","Id_Parent":"relation/3819422","Index":12,"Name_Child":"Lamotrek","Name_Parent":"Yap"},{"AdminLevel_Child":"4","AdminLevel_Parent":"2","Children":"relation/3821455, relation/3821702, relation/3821703, relation/3821704, relation/3821705, relation/3821706, relation/3821708, relation/3821709, relation/3821710, relation/3821712, relation/3821713, relation/3821714, relation/3821715, relation/3823271, relation/3823272, relation/3823273, relation/3823274, relation/3823275, relation/3823276, relation/3823277, relation/3823278, relation/3823279, relation/3823280, relation/3823281, relation/3823282, relation/3823283, relation/3823284, relation/3823285, relation/3823286, relation/3823287, relation/3823288, relation/3823289, relation/3823290, relation/3823291, relation/3823292, relation/3823293, relation/3823294, relation/3823295, relation/3823296, relation/3823297","ChildrenIndexes":"21, 22, 23, 24, 25, 26, 27, 28, 29, 30, 31, 32, 33, 34, 35, 36, 37, 38, 39, 40, 41, 42, 43, 44, 45, 46, 47, 48, 49, 50, 51, 52, 53, 54, 55, 56, 57, 58, 59, 60","CountryCode_Child":"FM","CountryCode_Parent":"FM","Id":3819479,"Id_Child":"relation/3819479","Id_Parent":"relation/571802","Index":13,"Name_Child":"Chuuk","Name_Parent":"Micronesia / Federated States of Micronesia"},{"AdminLevel_Child":"4","AdminLevel_Parent":"2","Children":"relation/3819490, relation/3819491, relation/3819492, relation/3819493","ChildrenIndexes":"16, 17, 18, 19","CountryCode_Child":"FM","CountryCode_Parent":"FM","Id":3819480,"Id_Child":"relation/3819480","Id_Parent":"relation/571802","Index":14,"Name_Child":"Kosrae","Name_Parent":"Micronesia / Federated States of Micronesia"},{"AdminLevel_Child":"4","AdminLevel_Parent":"2","Children":"relation/3819499, relation/3823801, relation/3823802, relation/3823804, relation/3823809, relation/3823810","ChildrenIndexes":"20, 61, 62, 63, 64, 65","CountryCode_Child":"FM","CountryCode_Parent":"FM","Id":3819481,"Id_Child":"relation/3819481","Id_Parent":"relation/571802","Index":15,"Name_Child":"Pohnpei","Name_Parent":"Micronesia / Federated States of Micronesia"},{"AdminLevel_Child":"8","AdminLevel_Parent":"4","Children":"","ChildrenIndexes":"","CountryCode_Child":"FM","CountryCode_Parent":"FM","Id":3819490,"Id_Child":"relation/3819490","Id_Parent":"relation/3819480","Index":16,"Name_Child":"Lelu","Name_Parent":"Kosrae"},{"AdminLevel_Child":"8","AdminLevel_Parent":"4","Children":"","ChildrenIndexes":"","CountryCode_Child":"FM","CountryCode_Parent":"FM","Id":3819491,"Id_Child":"relation/3819491","Id_Parent":"relation/3819480","Index":17,"Name_Child":"Malem","Name_Parent":"Kosrae"},{"AdminLevel_Child":"8","AdminLevel_Parent":"4","Children":"","ChildrenIndexes":"","CountryCode_Child":"FM","CountryCode_Parent":"FM","Id":3819492,"Id_Child":"relation/3819492","Id_Parent":"relation/3819480","Index":18,"Name_Child":"Tafunsak","Name_Parent":"Kosrae"},{"AdminLevel_Child":"8","AdminLevel_Parent":"4","Children":"","ChildrenIndexes":"","CountryCode_Child":"FM","CountryCode_Parent":"FM","Id":3819493,"Id_Child":"relation/3819493","Id_Parent":"relation/3819480","Index":19,"Name_Child":"Utwe","Name_Parent":"Kosrae"},{"AdminLevel_Child":"8","AdminLevel_Parent":"4","Children":"","ChildrenIndexes":"","CountryCode_Child":"FM","CountryCode_Parent":"FM","Id":3819499,"Id_Child":"relation/3819499","Id_Parent":"relation/3819481","Index":20,"Name_Child":"Kitti","Name_Parent":"Pohnpei"},{"AdminLevel_Child":"8","AdminLevel_Parent":"4","Children":"","ChildrenIndexes":"","CountryCode_Child":"FM","CountryCode_Parent":"FM","Id":3821455,"Id_Child":"relation/3821455","Id_Parent":"relation/3819479","Index":21,"Name_Child":"Weno","Name_Parent":"Chuuk"},{"AdminLevel_Child":"8","AdminLevel_Parent":"4","Children":"","ChildrenIndexes":"","CountryCode_Child":"FM","CountryCode_Parent":"FM","Id":3821702,"Id_Child":"relation/3821702","Id_Parent":"relation/3819479","Index":22,"Name_Child":"Fala-Beguets","Name_Parent":"Chuuk"},{"AdminLevel_Child":"8","AdminLevel_Parent":"4","Children":"","ChildrenIndexes":"","CountryCode_Child":"FM","CountryCode_Parent":"FM","Id":3821703,"Id_Child":"relation/3821703","Id_Parent":"relation/3819479","Index":23,"Name_Child":"Fananu","Name_Parent":"Chuuk"},{"AdminLevel_Child":"8","AdminLevel_Parent":"4","Children":"","ChildrenIndexes":"","CountryCode_Child":"FM","CountryCode_Parent":"FM","Id":3821704,"Id_Child":"relation/3821704","Id_Parent":"relation/3819479","Index":24,"Name_Child":"Fefan","Name_Parent":"Chuuk"},{"AdminLevel_Child":"8","AdminLevel_Parent":"4","Children":"","ChildrenIndexes":"","CountryCode_Child":"FM","CountryCode_Parent":"FM","Id":3821705,"Id_Child":"relation/3821705","Id_Parent":"relation/3819479","Index":25,"Name_Child":"Pis-Losap","Name_Parent":"Chuuk"},{"AdminLevel_Child":"8","AdminLevel_Parent":"4","Children":"","ChildrenIndexes":"","CountryCode_Child":"FM","CountryCode_Parent":"FM","Id":3821706,"Id_Child":"relation/3821706","Id_Parent":"relation/3819479","Index":26,"Name_Child":"Param","Name_Parent":"Chuuk"},{"AdminLevel_Child":"8","AdminLevel_Parent":"4","Children":"","ChildrenIndexes":"","CountryCode_Child":"FM","CountryCode_Parent":"FM","Id":3821708,"Id_Child":"relation/3821708","Id_Parent":"relation/3819479","Index":27,"Name_Child":"Romanum","Name_Parent":"Chuuk"},{"AdminLevel_Child":"8","AdminLevel_Parent":"4","Children":"","ChildrenIndexes":"","CountryCode_Child":"FM","CountryCode_Parent":"FM","Id":3821709,"Id_Child":"relation/3821709","Id_Parent":"relation/3819479","Index":28,"Name_Child":"Tol","Name_Parent":"Chuuk"},{"AdminLevel_Child":"8","AdminLevel_Parent":"4","Children":"","ChildrenIndexes":"","CountryCode_Child":"FM","CountryCode_Parent":"FM","Id":3821710,"Id_Child":"relation/3821710","Id_Parent":"relation/3819479","Index":29,"Name_Child":"Tonowas","Name_Parent":"Chuuk"},{"AdminLevel_Child":"8","AdminLevel_Parent":"4","Children":"","ChildrenIndexes":"","CountryCode_Child":"FM","CountryCode_Parent":"FM","Id":3821712,"Id_Child":"relation/3821712","Id_Parent":"relation/3819479","Index":30,"Name_Child":"Tsis","Name_Parent":"Chuuk"},{"AdminLevel_Child":"8","AdminLevel_Parent":"4","Children":"","ChildrenIndexes":"","CountryCode_Child":"FM","CountryCode_Parent":"FM","Id":3821713,"Id_Child":"relation/3821713","Id_Parent":"relation/3819479","Index":31,"Name_Child":"Udot","Name_Parent":"Chuuk"},{"AdminLevel_Child":"8","AdminLevel_Parent":"4","Children":"","ChildrenIndexes":"","CountryCode_Child":"FM","CountryCode_Parent":"FM","Id":3821714,"Id_Child":"relation/3821714","Id_Parent":"relation/3819479","Index":32,"Name_Child":"Uman","Name_Parent":"Chuuk"},{"AdminLevel_Child":"8","AdminLevel_Parent":"4","Children":"","ChildrenIndexes":"","CountryCode_Child":"FM","CountryCode_Parent":"FM","Id":3821715,"Id_Child":"relation/3821715","Id_Parent":"relation/3819479","Index":33,"Name_Child":"Ulul","Name_Parent":"Chuuk"},{"AdminLevel_Child":"8","AdminLevel_Parent":"4","Children":"","ChildrenIndexes":"","CountryCode_Child":"FM","CountryCode_Parent":"FM","Id":3823271,"Id_Child":"relation/3823271","Id_Parent":"relation/3819479","Index":34,"Name_Child":"Eot","Name_Parent":"Chuuk"},{"AdminLevel_Child":"8","AdminLevel_Parent":"4","Children":"","ChildrenIndexes":"","CountryCode_Child":"FM","CountryCode_Parent":"FM","Id":3823272,"Id_Child":"relation/3823272","Id_Parent":"relation/3819479","Index":35,"Name_Child":"Ettal","Name_Parent":"Chuuk"},{"AdminLevel_Child":"8","AdminLevel_Parent":"4","Children":"","ChildrenIndexes":"","CountryCode_Child":"FM","CountryCode_Parent":"FM","Id":3823273,"Id_Child":"relation/3823273","Id_Parent":"relation/3819479","Index":36,"Name_Child":"Fono","Name_Parent":"Chuuk"},{"AdminLevel_Child":"8","AdminLevel_Parent":"4","Children":"","ChildrenIndexes":"","CountryCode_Child":"FM","CountryCode_Parent":"FM","Id":3823274,"Id_Child":"relation/3823274","Id_Parent":"relation/3819479","Index":37,"Name_Child":"Kutu","Name_Parent":"Chuuk"},{"AdminLevel_Child":"8","AdminLevel_Parent":"4","Children":"","ChildrenIndexes":"","CountryCode_Child":"FM","CountryCode_Parent":"FM","Id":3823275,"Id_Child":"relation/3823275","Id_Parent":"relation/3819479","Index":38,"Name_Child":"Losap","Name_Parent":"Chuuk"},{"AdminLevel_Child":"8","AdminLevel_Parent":"4","Children":"","ChildrenIndexes":"","CountryCode_Child":"FM","CountryCode_Parent":"FM","Id":3823276,"Id_Child":"relation/3823276","Id_Parent":"relation/3819479","Index":39,"Name_Child":"Lukunor","Name_Parent":"Chuuk"},{"AdminLevel_Child":"8","AdminLevel_Parent":"4","Children":"","ChildrenIndexes":"","CountryCode_Child":"FM","CountryCode_Parent":"FM","Id":3823277,"Id_Child":"relation/3823277","Id_Parent":"relation/3819479","Index":40,"Name_Child":"Magur","Name_Parent":"Chuuk"},{"AdminLevel_Child":"8","AdminLevel_Parent":"4","Children":"","ChildrenIndexes":"","CountryCode_Child":"FM","CountryCode_Parent":"FM","Id":3823278,"Id_Child":"relation/3823278","Id_Parent":"relation/3819479","Index":41,"Name_Child":"Moch","Name_Parent":"Chuuk"},{"AdminLevel_Child":"8","AdminLevel_Parent":"4","Children":"","ChildrenIndexes":"","CountryCode_Child":"FM","CountryCode_Parent":"FM","Id":3823279,"Id_Child":"relation/3823279","Id_Parent":"relation/3819479","Index":42,"Name_Child":"Murilo","Name_Parent":"Chuuk"},{"AdminLevel_Child":"8","AdminLevel_Parent":"4","Children":"","ChildrenIndexes":"","CountryCode_Child":"FM","CountryCode_Parent":"FM","Id":3823280,"Id_Child":"relation/3823280","Id_Parent":"relation/3819479","Index":43,"Name_Child":"Nama","Name_Parent":"Chuuk"},{"AdminLevel_Child":"8","AdminLevel_Parent":"4","Children":"","ChildrenIndexes":"","CountryCode_Child":"FM","CountryCode_Parent":"FM","Id":3823281,"Id_Child":"relation/3823281","Id_Parent":"relation/3819479","Index":44,"Name_Child":"Namoluk","Name_Parent":"Chuuk"},{"AdminLevel_Child":"8","AdminLevel_Parent":"4","Children":"","ChildrenIndexes":"","CountryCode_Child":"FM","CountryCode_Parent":"FM","Id":3823282,"Id_Child":"relation/3823282","Id_Parent":"relation/3819479","Index":45,"Name_Child":"Nomwin","Name_Parent":"Chuuk"},{"AdminLevel_Child":"8","AdminLevel_Parent":"4","Children":"","ChildrenIndexes":"","CountryCode_Child":"FM","CountryCode_Parent":"FM","Id":3823283,"Id_Child":"relation/3823283","Id_Parent":"relation/3819479","Index":46,"Name_Child":"Onari","Name_Parent":"Chuuk"},{"AdminLevel_Child":"8","AdminLevel_Parent":"4","Children":"","ChildrenIndexes":"","CountryCode_Child":"FM","CountryCode_Parent":"FM","Id":3823284,"Id_Child":"relation/3823284","Id_Parent":"relation/3819479","Index":47,"Name_Child":"Oneop","Name_Parent":"Chuuk"},{"AdminLevel_Child":"8","AdminLevel_Parent":"4","Children":"","ChildrenIndexes":"","CountryCode_Child":"FM","CountryCode_Parent":"FM","Id":3823285,"Id_Child":"relation/3823285","Id_Parent":"relation/3819479","Index":48,"Name_Child":"Ono","Name_Parent":"Chuuk"},{"AdminLevel_Child":"8","AdminLevel_Parent":"4","Children":"","ChildrenIndexes":"","CountryCode_Child":"FM","CountryCode_Parent":"FM","Id":3823286,"Id_Child":"relation/3823286","Id_Parent":"relation/3819479","Index":49,"Name_Child":"Paata","Name_Parent":"Chuuk"},{"AdminLevel_Child":"8","AdminLevel_Parent":"4","Children":"","ChildrenIndexes":"","CountryCode_Child":"FM","CountryCode_Parent":"FM","Id":3823287,"Id_Child":"relation/3823287","Id_Parent":"relation/3819479","Index":50,"Name_Child":"Pis-Paneu","Name_Parent":"Chuuk"},{"AdminLevel_Child":"8","AdminLevel_Parent":"4","Children":"","ChildrenIndexes":"","CountryCode_Child":"FM","CountryCode_Parent":"FM","Id":3823288,"Id_Child":"relation/3823288","Id_Parent":"relation/3819479","Index":51,"Name_Child":"Pisaras","Name_Parent":"Chuuk"},{"AdminLevel_Child":"8","AdminLevel_Parent":"4","Children":"","ChildrenIndexes":"","CountryCode_Child":"FM","CountryCode_Parent":"FM","Id":3823289,"Id_Child":"relation/3823289","Id_Parent":"relation/3819479","Index":52,"Name_Child":"Polle","Name_Parent":"Chuuk"},{"AdminLevel_Child":"8","AdminLevel_Parent":"4","Children":"","ChildrenIndexes":"","CountryCode_Child":"FM","CountryCode_Parent":"FM","Id":3823290,"Id_Child":"relation/3823290","Id_Parent":"relation/3819479","Index":53,"Name_Child":"Pulap","Name_Parent":"Chuuk"},{"AdminLevel_Child":"8","AdminLevel_Parent":"4","Children":"","ChildrenIndexes":"","CountryCode_Child":"FM","CountryCode_Parent":"FM","Id":3823291,"Id_Child":"relation/3823291","Id_Parent":"relation/3819479","Index":54,"Name_Child":"Pulusuk","Name_Parent":"Chuuk"},{"AdminLevel_Child":"8","AdminLevel_Parent":"4","Children":"","ChildrenIndexes":"","CountryCode_Child":"FM","CountryCode_Parent":"FM","Id":3823292,"Id_Child":"relation/3823292","Id_Parent":"relation/3819479","Index":55,"Name_Child":"Puluwat","Name_Parent":"Chuuk"},{"AdminLevel_Child":"8","AdminLevel_Parent":"4","Children":"","ChildrenIndexes":"","CountryCode_Child":"FM","CountryCode_Parent":"FM","Id":3823293,"Id_Child":"relation/3823293","Id_Parent":"relation/3819479","Index":56,"Name_Child":"Ruo","Name_Parent":"Chuuk"},{"AdminLevel_Child":"8","AdminLevel_Parent":"4","Children":"","ChildrenIndexes":"","CountryCode_Child":"FM","CountryCode_Parent":"FM","Id":3823294,"Id_Child":"relation/3823294","Id_Parent":"relation/3819479","Index":57,"Name_Child":"Satawan","Name_Parent":"Chuuk"},{"AdminLevel_Child":"8","AdminLevel_Parent":"4","Children":"","ChildrenIndexes":"","CountryCode_Child":"FM","CountryCode_Parent":"FM","Id":3823295,"Id_Child":"relation/3823295","Id_Parent":"relation/3819479","Index":58,"Name_Child":"Ta","Name_Parent":"Chuuk"},{"AdminLevel_Child":"8","AdminLevel_Parent":"4","Children":"","ChildrenIndexes":"","CountryCode_Child":"FM","CountryCode_Parent":"FM","Id":3823296,"Id_Child":"relation/3823296","Id_Parent":"relation/3819479","Index":59,"Name_Child":"Tamatam","Name_Parent":"Chuuk"},{"AdminLevel_Child":"8","AdminLevel_Parent":"4","Children":"","ChildrenIndexes":"","CountryCode_Child":"FM","CountryCode_Parent":"FM","Id":3823297,"Id_Child":"relation/3823297","Id_Parent":"relation/3819479","Index":60,"Name_Child":"Wonei","Name_Parent":"Chuuk"},{"AdminLevel_Child":"8","AdminLevel_Parent":"4","Children":"","ChildrenIndexes":"","CountryCode_Child":"FM","CountryCode_Parent":"FM","Id":3823801,"Id_Child":"relation/3823801","Id_Parent":"relation/3819481","Index":61,"Name_Child":"Kolonia","Name_Parent":"Pohnpei"},{"AdminLevel_Child":"8","AdminLevel_Parent":"4","Children":"","ChildrenIndexes":"","CountryCode_Child":"FM","CountryCode_Parent":"FM","Id":3823802,"Id_Child":"relation/3823802","Id_Parent":"relation/3819481","Index":62,"Name_Child":"Madolenihmw","Name_Parent":"Pohnpei"},{"AdminLevel_Child":"8","AdminLevel_Parent":"4","Children":"","ChildrenIndexes":"","CountryCode_Child":"FM","CountryCode_Parent":"FM","Id":3823804,"Id_Child":"relation/3823804","Id_Parent":"relation/3819481","Index":63,"Name_Child":"Nett","Name_Parent":"Pohnpei"},{"AdminLevel_Child":"8","AdminLevel_Parent":"4","Children":"","ChildrenIndexes":"","CountryCode_Child":"FM","CountryCode_Parent":"FM","Id":3823809,"Id_Child":"relation/3823809","Id_Parent":"relation/3819481","Index":64,"Name_Child":"Sokehs","Name_Parent":"Pohnpei"},{"AdminLevel_Child":"8","AdminLevel_Parent":"4","Children":"","ChildrenIndexes":"","CountryCode_Child":"FM","CountryCode_Parent":"FM","Id":3823810,"Id_Child":"relation/3823810","Id_Parent":"relation/3819481","Index":65,"Name_Child":"U","Name_Parent":"Pohnpei"}]