[{"AdminLevel_Child":"5","AdminLevel_Parent":"2","Children":"","ChildrenIndexes":"","CountryCode_Child":"LS","CountryCode_Parent":"LS","Id":1252920,"Id_Child":"relation/1252920","Id_Parent":"relation/2093234","Index":0,"Name_Child":"Mokhotlong District","Name_Parent":"Lesotho"},{"AdminLevel_Child":"5","AdminLevel_Parent":"2","Children":"","ChildrenIndexes":"","CountryCode_Child":"LS","CountryCode_Parent":"LS","Id":1252921,"Id_Child":"relation/1252921","Id_Parent":"relation/2093234","Index":1,"Name_Child":"Maseru District","Name_Parent":"Lesotho"},{"AdminLevel_Child":"5","AdminLevel_Parent":"2","Children":"","ChildrenIndexes":"","CountryCode_Child":"LS","CountryCode_Parent":"LS","Id":1252922,"Id_Child":"relation/1252922","Id_Parent":"relation/2093234","Index":2,"Name_Child":"Butha-Buthe District","Name_Parent":"Lesotho"},{"AdminLevel_Child":"5","AdminLevel_Parent":"2","Children":"","ChildrenIndexes":"","CountryCode_Child":"LS","CountryCode_Parent":"LS","Id":1252923,"Id_Child":"relation/1252923","Id_Parent":"relation/2093234","Index":3,"Name_Child":"Mohale's Hoek District","Name_Parent":"Lesotho"},{"AdminLevel_Child":"5","AdminLevel_Parent":"2","Children":"","ChildrenIndexes":"","CountryCode_Child":"LS","CountryCode_Parent":"LS","Id":1252924,"Id_Child":"relation/1252924","Id_Parent":"relation/2093234","Index":4,"Name_Child":"Mafeteng District","Name_Parent":"Lesotho"},{"AdminLevel_Child":"5","AdminLevel_Parent":"2","Children":"","ChildrenIndexes":"","CountryCode_Child":"LS","CountryCode_Parent":"LS","Id":1252925,"Id_Child":"relation/1252925","Id_Parent":"relation/2093234","Index":5,"Name_Child":"Quthing District","Name_Parent":"Lesotho"},{"AdminLevel_Child":"5","AdminLevel_Parent":"2","Children":"","ChildrenIndexes":"","CountryCode_Child":"LS","CountryCode_Parent":"LS","Id":1252926,"Id_Child":"relation/1252926","Id_Parent":"relation/2093234","Index":6,"Name_Child":"Berea District","Name_Parent":"Lesotho"},{"AdminLevel_Child":"5","AdminLevel_Parent":"2","Children":"","ChildrenIndexes":"","CountryCode_Child":"LS","CountryCode_Parent":"LS","Id":1252927,"Id_Child":"relation/1252927","Id_Parent":"relation/2093234","Index":7,"Name_Child":"Thaba-Tseka District","Name_Parent":"Lesotho"},{"AdminLevel_Child":"5","AdminLevel_Parent":"2","Children":"","ChildrenIndexes":"","CountryCode_Child":"LS","CountryCode_Parent":"LS","Id":1252928,"Id_Child":"relation/1252928","Id_Parent":"relation/2093234","Index":8,"Name_Child":"Qacha's Nek District","Name_Parent":"Lesotho"},{"AdminLevel_Child":"5","AdminLevel_Parent":"2","Children":"","ChildrenIndexes":"","CountryCode_Child":"LS","CountryCode_Parent":"LS","Id":1252929,"Id_Child":"relation/1252929","Id_Parent":"relation/2093234","Index":9,"Name_Child":"Leribe District","Name_Parent":"Lesotho"}]