[{"AdminLevel_Child":"4","AdminLevel_Parent":"2","Children":"","ChildrenIndexes":"","CountryCode_Child":"WS","CountryCode_Parent":"WS","Id":13285389,"Id_Child":"relation/13285389","Id_Parent":"relation/1872673","Index":0,"Name_Child":"Vaisigano","Name_Parent":"Sāmoa / Samoa"},{"AdminLevel_Child":"4","AdminLevel_Parent":"2","Children":"","ChildrenIndexes":"","CountryCode_Child":"WS","CountryCode_Parent":"WS","Id":13285390,"Id_Child":"relation/13285390","Id_Parent":"relation/1872673","Index":1,"Name_Child":"Satupaʻitea","Name_Parent":"Sāmoa / Samoa"},{"AdminLevel_Child":"4","AdminLevel_Parent":"2","Children":"","ChildrenIndexes":"","CountryCode_Child":"WS","CountryCode_Parent":"WS","Id":13285391,"Id_Child":"relation/13285391","Id_Parent":"relation/1872673","Index":2,"Name_Child":"Palauli","Name_Parent":"Sāmoa / Samoa"},{"AdminLevel_Child":"4","AdminLevel_Parent":"2","Children":"","ChildrenIndexes":"","CountryCode_Child":"WS","CountryCode_Parent":"WS","Id":13285392,"Id_Child":"relation/13285392","Id_Parent":"relation/1872673","Index":3,"Name_Child":"Faʻasaleleaga","Name_Parent":"Sāmoa / Samoa"},{"AdminLevel_Child":"4","AdminLevel_Parent":"2","Children":"","ChildrenIndexes":"","CountryCode_Child":"WS","CountryCode_Parent":"WS","Id":13285429,"Id_Child":"relation/13285429","Id_Parent":"relation/1872673","Index":4,"Name_Child":"Gagaʻifomauga","Name_Parent":"Sāmoa / Samoa"},{"AdminLevel_Child":"4","AdminLevel_Parent":"2","Children":"","ChildrenIndexes":"","CountryCode_Child":"WS","CountryCode_Parent":"WS","Id":13285430,"Id_Child":"relation/13285430","Id_Parent":"relation/1872673","Index":5,"Name_Child":"Gagaʻemauga","Name_Parent":"Sāmoa / Samoa"},{"AdminLevel_Child":"4","AdminLevel_Parent":"2","Children":"","ChildrenIndexes":"","CountryCode_Child":"WS","CountryCode_Parent":"WS","Id":13285778,"Id_Child":"relation/13285778","Id_Parent":"relation/1872673","Index":6,"Name_Child":"Aiga-i-le-Tai","Name_Parent":"Sāmoa / Samoa"},{"AdminLevel_Child":"4","AdminLevel_Parent":"2","Children":"","ChildrenIndexes":"","CountryCode_Child":"WS","CountryCode_Parent":"WS","Id":13285779,"Id_Child":"relation/13285779","Id_Parent":"relation/1872673","Index":7,"Name_Child":"Vaʻa-o-Fonoti","Name_Parent":"Sāmoa / Samoa"},{"AdminLevel_Child":"4","AdminLevel_Parent":"2","Children":"","ChildrenIndexes":"","CountryCode_Child":"WS","CountryCode_Parent":"WS","Id":13285780,"Id_Child":"relation/13285780","Id_Parent":"relation/1872673","Index":8,"Name_Child":"Ātua","Name_Parent":"Sāmoa / Samoa"},{"AdminLevel_Child":"4","AdminLevel_Parent":"2","Children":"","ChildrenIndexes":"","CountryCode_Child":"WS","CountryCode_Parent":"WS","Id":13285808,"Id_Child":"relation/13285808","Id_Parent":"relation/1872673","Index":9,"Name_Child":"Tuamasaga","Name_Parent":"Sāmoa / Samoa"},{"AdminLevel_Child":"4","AdminLevel_Parent":"2","Children":"","ChildrenIndexes":"","CountryCode_Child":"WS","CountryCode_Parent":"WS","Id":13285809,"Id_Child":"relation/13285809","Id_Parent":"relation/1872673","Index":10,"Name_Child":"Aʻana","Name_Parent":"Sāmoa / Samoa"},{"AdminLevel_Child":"4","AdminLevel_Parent":"2","Children":"","ChildrenIndexes":"","CountryCode_Child":"WS","CountryCode_Parent":"WS","Id":13288385,"Id_Child":"relation/13288385","Id_Parent":"relation/1872673","Index":11,"Name_Child":"Namuʻa","Name_Parent":"Sāmoa / Samoa"},{"AdminLevel_Child":"4","AdminLevel_Parent":"2","Children":"","ChildrenIndexes":"","CountryCode_Child":"WS","CountryCode_Parent":"WS","Id":13288386,"Id_Child":"relation/13288386","Id_Parent":"relation/1872673","Index":12,"Name_Child":"Fanuatapu","Name_Parent":"Sāmoa / Samoa"}]